{
  "fuente": "bonistas.com (endpoint interno, no oficial/no documentado), liquidacion 24hs",
  "actualizado": "2026-07-03T05:12:42.109806+00:00",
  "categorias": {
    "tasa_fija": [
      {
        "ticker": "S17L6",
        "familia": "LETRAS-FIJO",
        "vencimiento": "2026-07-17",
        "tna": 0.26843002680328887,
        "duration": 0.0231103695558956,
        "precio": 107.06,
        "paridad": 0.9995726794458807,
        "descripcion": "Bono Tasa Fija ARS - 29.23% - vto. 07/2026"
      },
      {
        "ticker": "S31L6",
        "familia": "LETRAS-FIJO",
        "vencimiento": "2026-07-31",
        "tna": 0.23318820078372493,
        "duration": 0.054368357238264844,
        "precio": 115.83,
        "paridad": 1.0044231331304976,
        "descripcion": "Bono Tasa Fija ARS - 38.48% - vto. 07/2026"
      },
      {
        "ticker": "S14G6",
        "familia": "LETRAS-FIJO",
        "vencimiento": "2026-08-14",
        "tna": 0.24985759580627676,
        "duration": 0.08343998441305313,
        "precio": 105.351,
        "paridad": 0.997998238675506,
        "descripcion": "Bono Tasa Fija ARS - 26.82% - vto. 08/2026"
      },
      {
        "ticker": "S31G6",
        "familia": "LETRAS-FIJO",
        "vencimiento": "2026-08-31",
        "tna": 0.22989550169499218,
        "duration": 0.1221791671633659,
        "precio": 122.701,
        "paridad": 1.0061700853394195,
        "descripcion": "Bono Tasa Fija ARS - 34.49% - vto. 08/2026"
      },
      {
        "ticker": "S30S6",
        "familia": "LETRAS-FIJO",
        "vencimiento": "2026-09-30",
        "tna": 0.2343823516918473,
        "duration": 0.18680820646702376,
        "precio": 111.28,
        "paridad": 1.0121619456336057,
        "descripcion": "Bono Tasa Fija ARS - 34.96% - vto. 09/2026"
      },
      {
        "ticker": "TO26",
        "familia": "BONO-FIJA",
        "vencimiento": "2026-10-17",
        "tna": 0.2287603908388265,
        "duration": 0.25521580648236125,
        "precio": 100.95,
        "paridad": 0.9762924955338554,
        "descripcion": "Bono Tasa Fija ARS - 15.50% - vto. 10/2026"
      },
      {
        "ticker": "S30O6",
        "familia": "LETRAS-FIJO",
        "vencimiento": "2026-10-30",
        "tna": 0.2307575220172433,
        "duration": 0.25287145197512284,
        "precio": 125.8,
        "paridad": 1.013643054035693,
        "descripcion": "Bono Tasa Fija ARS - 35.28% - vto. 10/2026"
      },
      {
        "ticker": "S30N6",
        "familia": "LETRAS-FIJO",
        "vencimiento": "2026-11-30",
        "tna": 0.22362273308455016,
        "duration": 0.3227008973522981,
        "precio": 118.8,
        "paridad": 1.011811788763053,
        "descripcion": "Bono Tasa Fija ARS - 31.37% - vto. 11/2026"
      },
      {
        "ticker": "T15E7",
        "familia": "BONO-FIJA",
        "vencimiento": "2027-01-15",
        "tna": 0.22421656221369712,
        "duration": 0.4234352162234359,
        "precio": 143.249,
        "paridad": 0.9898166549123452,
        "descripcion": "Bono Tasa Fija ARS - 27.57% - vto. 01/2027"
      },
      {
        "ticker": "T30A7",
        "familia": "BONO-FIJA",
        "vencimiento": "2027-04-30",
        "tna": 0.2308180933611279,
        "duration": 0.6495794358392436,
        "precio": 130.55,
        "paridad": 1.035108692245275,
        "descripcion": "Bono Tasa Fija ARS - 35.28% - vto. 04/2027"
      },
      {
        "ticker": "T31Y7",
        "familia": "BONO-FIJA",
        "vencimiento": "2027-05-31",
        "tna": 0.22978563586620293,
        "duration": 0.7178799911449206,
        "precio": 123.45,
        "paridad": 1.031296879877226,
        "descripcion": "Bono Tasa Fija ARS - 32.92% - vto. 05/2027"
      },
      {
        "ticker": "T30J7",
        "familia": "BONO-FIJA",
        "vencimiento": "2027-06-30",
        "tna": 0.22596364121917834,
        "duration": 0.7862838179491378,
        "precio": 125.2,
        "paridad": 1.0594005813400578,
        "descripcion": "Bono Tasa Fija ARS - 35.75% - vto. 06/2027"
      }
    ],
    "cer": [
      {
        "ticker": "TZXO6",
        "familia": "BONO-CER",
        "vencimiento": "2026-10-30",
        "tna": 0.02349127469238166,
        "duration": 0.310436634599213,
        "precio": 164.3,
        "paridad": 0.9925820791930744,
        "descripcion": "Bono CER - vto. 10/2026"
      },
      {
        "ticker": "TX26",
        "familia": "BONO-CER",
        "vencimiento": "2026-11-09",
        "tna": 0.025558485492280347,
        "duration": 0.3407989454673553,
        "precio": 705.9,
        "paridad": 0.997977271321298,
        "descripcion": "Bono CER - vto. 11/2026"
      },
      {
        "ticker": "TZXD6",
        "familia": "BONO-CER",
        "vencimiento": "2026-12-15",
        "tna": 0.0308300302047968,
        "duration": 0.43037794586162886,
        "precio": 289.25,
        "paridad": 0.9864350956805571,
        "descripcion": "Bono CER - vto. 12/2026"
      },
      {
        "ticker": "TZXM7",
        "familia": "BONO-CER",
        "vencimiento": "2027-03-31",
        "tna": 0.04329177104537418,
        "duration": 0.7031927513896508,
        "precio": 213.1,
        "paridad": 0.968773271474641,
        "descripcion": "Bono CER - vto. 03/2027"
      },
      {
        "ticker": "TZXA7",
        "familia": "LETRAS-CER",
        "vencimiento": "2027-04-30",
        "tna": 0.032311197443376294,
        "duration": 0.790514213669387,
        "precio": 118.75,
        "paridad": 0.9740088772077348,
        "descripcion": "Bono CER - vto. 04/2027"
      },
      {
        "ticker": "TZXY7",
        "familia": "LETRAS-CER",
        "vencimiento": "2027-05-31",
        "tna": 0.03923850282399677,
        "duration": 0.8667418541269138,
        "precio": 116.3,
        "paridad": 0.9652990739359124,
        "descripcion": "Bono CER - vto. 05/2027"
      },
      {
        "ticker": "TZX27",
        "familia": "BONO-CER",
        "vencimiento": "2027-06-30",
        "tna": 0.049257916725351514,
        "duration": 0.9363817247726552,
        "precio": 377.9,
        "paridad": 0.9527921803895484,
        "descripcion": "Bono CER - vto. 06/2027"
      },
      {
        "ticker": "TZXS7",
        "familia": "LETRAS-CER",
        "vencimiento": "2027-09-30",
        "tna": 0.05908003747616153,
        "duration": 1.1648996061189671,
        "precio": 102.2,
        "paridad": 0.9297684444941378,
        "descripcion": "Bono CER - vto. 09/2027"
      },
      {
        "ticker": "TZXD7",
        "familia": "BONO-CER",
        "vencimiento": "2027-12-15",
        "tna": 0.06690657722553883,
        "duration": 1.3506452587951727,
        "precio": 266.3,
        "paridad": 0.90816824884955,
        "descripcion": "Bono CER - vto. 12/2027"
      },
      {
        "ticker": "TZXM8",
        "familia": "LETRAS-CER",
        "vencimiento": "2028-03-31",
        "tna": 0.07703159917617519,
        "duration": 1.6079792403032023,
        "precio": 96.2,
        "paridad": 0.8751832129191395,
        "descripcion": "Bono CER - vto. 03/2028"
      },
      {
        "ticker": "TZX28",
        "familia": "BONO-CER",
        "vencimiento": "2028-06-30",
        "tna": 0.07971981842878861,
        "duration": 1.8333332667191495,
        "precio": 338.75,
        "paridad": 0.8540840198649365,
        "descripcion": "Bono CER - vto. 06/2028"
      },
      {
        "ticker": "TZXS8",
        "familia": "LETRAS-CER",
        "vencimiento": "2028-09-29",
        "tna": 0.079452165674879,
        "duration": 2.0635247113459756,
        "precio": 92.1,
        "paridad": 0.8378833046762239,
        "descripcion": "Bono CER - vto. 09/2028"
      },
      {
        "ticker": "TX28",
        "familia": "BONO-CER",
        "vencimiento": "2028-11-09",
        "tna": 0.06503273613156235,
        "duration": 1.2590906412762686,
        "precio": 1673,
        "paridad": 0.9457189014071059,
        "descripcion": "Bono CER - vto. 11/2028"
      },
      {
        "ticker": "TZXM9",
        "familia": "LETRAS-CER",
        "vencimiento": "2029-03-28",
        "tna": 0.08123879526841282,
        "duration": 2.5140131547575773,
        "precio": 88.15,
        "paridad": 0.8019480272226834,
        "descripcion": "Bono CER - vto. 03/2029"
      },
      {
        "ticker": "TX31",
        "familia": "BONO-CER",
        "vencimiento": "2031-11-30",
        "tna": 0.07855775508183971,
        "duration": 2.793312613638022,
        "precio": 1449.5,
        "paridad": 0.8534471386295431,
        "descripcion": "Bono CER - vto. 11/2031"
      }
    ]
  }
}